django_members_roles/__init__.py
django_members_roles/admin.py
django_members_roles/app_settings.py
django_members_roles/apps.py
django_members_roles/decorators.py
django_members_roles/forms.py
django_members_roles/members_urls.py
django_members_roles/middleware.py
django_members_roles/models.py
django_members_roles/tasks.py
django_members_roles/tests.py
django_members_roles/urls.py
django_members_roles/views.py
django_members_roles/management/__init__.py
django_members_roles/migrations/0001_initial.py
django_members_roles/migrations/__init__.py
django_members_roles/static/django_members_roles/js/django_members_roles.js
django_members_roles/static/django_members_roles/js/project_url_actions.js
django_members_roles/static/django_members_roles/js/url_permission_required.js
django_members_roles/static/django_members_roles/lib/bootstrap-3.3.7-dist/css/bootstrap.min.css
django_members_roles/static/django_members_roles/lib/bootstrap-3.3.7-dist/fonts/glyphicons-halflings-regular.eot
django_members_roles/static/django_members_roles/lib/bootstrap-3.3.7-dist/fonts/glyphicons-halflings-regular.svg
django_members_roles/static/django_members_roles/lib/bootstrap-3.3.7-dist/fonts/glyphicons-halflings-regular.ttf
django_members_roles/static/django_members_roles/lib/bootstrap-3.3.7-dist/fonts/glyphicons-halflings-regular.woff
django_members_roles/static/django_members_roles/lib/bootstrap-3.3.7-dist/fonts/glyphicons-halflings-regular.woff2
django_members_roles/static/django_members_roles/lib/bootstrap-3.3.7-dist/js/bootstrap.min.js
django_members_roles/static/django_members_roles/lib/css/bootstrap.min.css
django_members_roles/static/django_members_roles/lib/js/bootstrap.min.js
django_members_roles/static/django_members_roles/lib/js/cowhite.js
django_members_roles/static/django_members_roles/lib/js/jquery.min.js
django_members_roles/templates/admin/django_members_roles/projecturl/change_list.html
django_members_roles-0.1.dist-info/METADATA
django_members_roles-0.1.dist-info/RECORD
django_members_roles-0.1.dist-info/WHEEL
django_members_roles-0.1.dist-info/top_level.txt
